MANIFEST.in
README.rst
setup.py
examples/get_posts.py
examples/appengine/app.yaml
examples/appengine/example.html
examples/appengine/example.py
examples/flask/config.py
examples/flask/requirements.txt
examples/flask/run.py
examples/flask/app/__init__.py
examples/flask/app/models.py
examples/flask/app/views.py
examples/flask/app/static/css/style.css
examples/flask/app/templates/base.html
examples/flask/app/templates/index.html
examples/flask/app/templates/login.html
examples/newsfeed/app.yaml
examples/newsfeed/facebookclient.py
examples/newsfeed/static/base.css
examples/newsfeed/static/favicon.ico
examples/newsfeed/static/robots.txt
examples/newsfeed/templates/base.html
examples/newsfeed/templates/home.html
examples/newsfeed/templates/index.html
examples/oauth/app.yaml
examples/oauth/facebookoauth.py
examples/oauth/oauth.html
examples/tornado/example.html
examples/tornado/example.py
examples/tornado/schema.sql
facebook/__init__.py
facebook/version.py
gc_facebook_sdk.egg-info/PKG-INFO
gc_facebook_sdk.egg-info/SOURCES.txt
gc_facebook_sdk.egg-info/dependency_links.txt
gc_facebook_sdk.egg-info/requires.txt
gc_facebook_sdk.egg-info/top_level.txt
test/test_facebook.py