Metadata-Version: 1.1
Name: gc-facebook-sdk
Version: 1.0.0-alpha
Summary: This client library is designed to support the Facebook Graph API and the official Facebook JavaScript SDK, which is the canonical way to implement Facebook authentication.
Home-page: https://github.com/pythonforfacebook/facebook-sdk
Author: Martey Dodoo
Author-email: facebook-sdk@marteydodoo.com
License: Apache
Platform: UNKNOWN
Classifier: License :: OSI Approved :: Apache Software License
Classifier: Programming Language :: Python :: 2.6
Classifier: Programming Language :: Python :: 2.7
Classifier: Programming Language :: Python :: 3.3
